webook/__init__.py
webook/cli.py
webook/commons.py
webook/main.py
webook/selectors.py
webook/urls.py
webook/web.py
webook-0.2.0.dist-info/METADATA
webook-0.2.0.dist-info/WHEEL
webook-0.2.0.dist-info/entry_points.txt
webook-0.2.0.dist-info/RECORD
